MANIFEST.in
README.md
requirements.txt
setup.cfg
setup.py
objection/__init__.py
objection/agent.js
objection/api/__init__.py
objection/api/app.py
objection/api/rpc.py
objection/api/script.py
objection/api/../agent.js
objection/api/../console/helpfiles/!.txt
objection/api/../console/helpfiles/android.clipboard.monitor.txt
objection/api/../console/helpfiles/android.clipboard.txt
objection/api/../console/helpfiles/android.heap.search.instances.txt
objection/api/../console/helpfiles/android.hooking.list.activities.txt
objection/api/../console/helpfiles/android.hooking.list.class_methods.txt
objection/api/../console/helpfiles/android.hooking.list.classes.txt
objection/api/../console/helpfiles/android.hooking.list.receivers.txt
objection/api/../console/helpfiles/android.hooking.list.services.txt
objection/api/../console/helpfiles/android.hooking.list.txt
objection/api/../console/helpfiles/android.hooking.search.classes.txt
objection/api/../console/helpfiles/android.hooking.search.methods.txt
objection/api/../console/helpfiles/android.hooking.search.txt
objection/api/../console/helpfiles/android.hooking.set.return_value.txt
objection/api/../console/helpfiles/android.hooking.txt
objection/api/../console/helpfiles/android.hooking.watch.class.txt
objection/api/../console/helpfiles/android.hooking.watch.class_method.txt
objection/api/../console/helpfiles/android.hooking.watch.txt
objection/api/../console/helpfiles/android.intent.launch_activity.txt
objection/api/../console/helpfiles/android.intent.launch_service.txt
objection/api/../console/helpfiles/android.intent.txt
objection/api/../console/helpfiles/android.keystore.clear.txt
objection/api/../console/helpfiles/android.keystore.list.txt
objection/api/../console/helpfiles/android.keystore.txt
objection/api/../console/helpfiles/android.keystore.watch.txt
objection/api/../console/helpfiles/android.root.disable.txt
objection/api/../console/helpfiles/android.root.simulate.txt
objection_ls.egg-info/PKG-INFO
objection_ls.egg-info/SOURCES.txt
objection_ls.egg-info/dependency_links.txt
objection_ls.egg-info/entry_points.txt
objection_ls.egg-info/requires.txt
objection_ls.egg-info/top_level.txt
