Metadata-Version: 1.2
Name: objection-ls
Version: 1.10.2
Summary: Instrumented Mobile Pentest Framework
Home-page: https://github.com/sensepost/objection
Author: Leon Jacobs - Edited by lamscun
Author-email: dreamhopeaaa@gmail.com
License: GPL v3
Download-URL: https://github.com/sensepost/objection/archive/1.10.2.tar.gz
Keywords: mobile,instrumentation,pentest,frida,hook
Platform: UNKNOWN
Classifier: Operating System :: OS Independent
Classifier: Natural Language :: English
Classifier: Programming Language :: Python :: 3 :: Only
Classifier: Programming Language :: JavaScript
Requires-Python: >=3.5
